{
  "name": "Don Erickson",
  "age": 32,
  "address": {
    "street": "Zaro Ridge",
    "city": "Sohdaho",
    "state": "WI",
    "zip": "35608"
  },
  "contact": {
    "phone": "(476) 915-6834",
    "servicePhone": "800991514"
  },
  "birthday": "1987-09-09T17:33:10.627Z",
  "ip": "126.151.194.17",
  "foo": "bar",
  "profile": {
    "about": "Gad vi poswindu ije wulkac sof iduzo ecliklat bi oriuhgu ebcofe cete. Siwlil hotavo cuv pe pi lun vuw pap gegi lagoc zavaz ilofu ri labpa imoef vilotac taav kowna. Hobijsog tut ke daj ah umhulo odu mupro defveeja na newet ekro mofog woc lafnadi dasoac dalow so. Le fopa muve mucec lumukupe dohe we juf verzic piudi pezma hop ohafolpar hiwuwicej uguta hebif pagtujso. Jedtamel uladazonu leppadbi ges ancinuc legifa cokecuwu uh gajvu cahagati vaofjo puniju daele powvi vitir iveov tajfu so. Mir juvotil wil cezgo up ge koz huchifnok vibere cano lahjew talpej nilhut moho. Pev nuhe ozlo oklurfi zah cocci firlol guri riaseso fukur tiolako inhu sajkaj.",
    "bio": "Vim irisuzwat nawendov wefud usasovhek kadci rapem sutzanvuv ujojes posozra ror hulehnob dafkavin jusziga sag eda udu. Zanenu uce nasozma fur hit posupsom faoruvu cuf sioni cuhek retoki soca boew. Rufanug bolos daludlu min mukkaktud obasi hapeh ji ka hemude okefe ozu. Sov le tic vomsegsa af arocemuh eja ku li fuh hupcivzos hebpascom ludmo lamlip zene lo."
  },
  "apiKey": "9f2dcf4842ddb60aa752e36822edefa49cb94cf0a26689ca38931c9dd38c505d",
  "currency": {
    "code": "SLL",
    "name": "Sierra Leone Leone"
  }
}