{
  "name": "Willie Fox",
  "age": 55,
  "address": {
    "street": "Pijhiv Turnpike",
    "city": "Nizzofnuc",
    "state": "KY",
    "zip": "05541"
  },
  "contact": {
    "phone": "(965) 568-7139",
    "servicePhone": "800453276"
  },
  "birthday": "1960-01-14T13:28:02.543Z",
  "ip": "165.250.161.58",
  "foo": "bar",
  "profile": {
    "about": "Bofud onuzi pizkit fazniceji ki ohu ifuluron baefujod domefliw kuwuv vezol cazorri diub dapge jomgi vet. Opudi bu niresepa ice zup fuwe lido gevogi jaz jicemu nafew ac kigdefma hu. Un fazowtob rirap sos us pih su zomcavme ul amawu kewlagve or. Sedag diz rej zik mato uze ono gotig ugo janvoh pagasug weh fohmi ciravu kumzuf bav. Orehovu divmov el tutujcef doipo ruod ofo kifler awgoju lisoho donetha him ocuzinaw ijjusi uh.",
    "bio": "Fegewe cehahwez won debi era lipegzip go doib degizi sa marerju na udusogbi. La deher hubwezto wo duej liw ka tanow hez sewrivos zum duh. Am hekboj uso beb sele iwoivijo gal pohno vijud se lal dapusa. Ocor hoife laiz ridior suv go vofew lahigu sovunug reded eb po ojlofwe dawoeji kofudjim huwadu viero. Wav pumocu agacu dadsal uce zeler dom waguni fu tuonwo sohzedsu iweko udo rivegaiz co jizniv to ret. Wejsunu igoekoben irarepa dele zopcauda buezku se gador tojro fopti cij ohosopov ro."
  },
  "apiKey": "099e5f76674d8df310cd1a68f5ef9f76bb2aebe061a8f503363f526ee424aefe",
  "currency": {
    "code": "JPY",
    "name": "Japan Yen"
  }
}