{
  "name": "Olga Black",
  "age": 39,
  "address": {
    "street": "Dojbe River",
    "city": "Lajagho",
    "state": "IL",
    "zip": "97528"
  },
  "contact": {
    "phone": "(742) 450-6060",
    "servicePhone": "800489528"
  },
  "birthday": "1991-11-17T21:15:41.445Z",
  "ip": "35.91.153.241",
  "foo": "bar",
  "profile": {
    "about": "Fava titeim tiwa huljuj fadhu vuvot haele sok ho hi wijomaj ehepoj. Weduhed cunanupu tautu weglajme ciw fo gercoig darehi cikhob ko fo ute pa pawjer wiva amponkuz. Pav zicpu eku bubhetek hopfe vijosoin ecjolku caek detnu joun co kisforac de mushakdi ifu miba. At pekughed dowaw bewviku bij mosi ebli cab ruttog rozlu kikmuwpu vuiczir ohevalid ruiju cuef kakuwlaw lamivaw coumad. Migojzor vuipo si dickoba deziseban valocsu ja palic jebzo lemuk se siweug cevuwe gosude lem bi. Posa aleolemup favbabdoj faka un sat ga vo we huriku gohangi ro ju jekuco pitipnuv ifiigab. Piwedca monu atbucpa akoasjec tov hewe pahne jovuddi likawis zoje emaleul inmese.",
    "bio": "Faclog irvinhu gu hivisam wu suttoan owirop bamrog ji merta nuvojde ogaz pabwujbu po ni effati. Gipona mem wuvumbo ladatiz megfof alda uptevfip gidov ru sah tef ir lukon. Ocokodet di muviid ufe wohotu ni megdesliz awgopti umgi zunejhah am buhceb ric. Wil boasla log ema zon pi mog setab defafu verejnu ze pamihi bid ite heakkos."
  },
  "apiKey": "d9e534582ddc83258eb9804f7562d8600562bd27ec9ee92fba00bdb6a8b85930",
  "currency": {
    "code": "GIP",
    "name": "Gibraltar Pound"
  }
}