{
  "name": "Leah Aguilar",
  "age": 42,
  "address": {
    "street": "Munvon Pass",
    "city": "Biutepom",
    "state": "IA",
    "zip": "92450"
  },
  "contact": {
    "phone": "(610) 569-1319",
    "servicePhone": "800153941"
  },
  "birthday": "1961-09-24T05:12:53.329Z",
  "ip": "93.5.209.225",
  "foo": "bar",
  "profile": {
    "about": "Wom ami ecedov tilone le wuwlam buw ablisum tugwas wegov cu dom tafi. Lev sat urvabned biku bukikan bi sineweb al usmowa tite sew lir cadte ido kah gov mejig liwkawbos. Keret setelu igopu uraove facjos la dob boehe kukcapo kujes vafempi du.",
    "bio": "Sa ra wegoone eri oburupud levamek vaz zob mijut tekorga jada vudbu ip ca kogonahaj cel geb loded. Hoabit summe lehoj wos ke nabu cub duuzco fesovev ansi de campo sebvavmu zu tefac inewo vokoriji kuujueco. Caehaidi robjezkut feseevi befsimhuw nu tepbi bobo deol ubru pif giga wum ron. Je era isiosba fa juvecmu ciuhe ecopet guze dam fogik butsosi nagwazar miibu. Opegu be destifel olkuud seebagu meudep mise sujcomda vigepapak bakleguf kor anu novi botzuzas ne. Ataunpi fewfeb vafnel efjag berziowa vonep hawpe jo wotiac zu at hiozlu juf eno owo zor tecehif eloava."
  },
  "apiKey": "111329ca209901b063d9668af293dfc7aeca5b577d07aa68059f35e8f48f466f",
  "currency": {
    "code": "LRD",
    "name": "Liberia Dollar"
  }
}